[{"id":2,"firstName":"Homero","lastName":"Simpsons","email":"homer_JS@ddd.com","password":"$2a$10$Kh8SfRy6JzfT27OjK7aAROgppPiCVBMVOuWjoMdfAaUyZxYyJveuW","admin":false,"image":"default-image.png"},{"id":3,"firstName":"cosme","lastName":"fulanito","email":"cosmefulanito@mail.com","password":"$2a$10$2PVWFnmQda3z9ooMFefD6uGBnGXWxvkwQJh9sf/VezuAmcN0iKNRy","admin":false,"image":"default-image.png"},{"id":4,"firstName":"max","lastName":"power","email":"mp@mail.com","password":"$2a$10$LXESmJ.NRJTWe0idtia7WezOe3c6TekRy/L6NLy7ZHjMFH42Fsw4S","admin":false,"image":"default-image.png"},{"id":5,"firstName":"franco","lastName":"fernandez","email":"franco@neotech.com","password":"$2a$10$aN/d4lYYgzYdMQ69JBXg6.kKFDMDHo7PtHzeuqNOPDKouq50QyzLy","admin":true,"image":"default-image.png"},{"id":6,"firstName":"ariel","lastName":"andrade","email":"ariel@neotech.com","password":"$2a$10$jFWwu2pc9Jwd7FxRbBbPouR4bfxDjONhtqdvxDxCoyXom9zsjgCH2","admin":true,"image":"default-image.png"},{"id":7,"firstName":"Homero","lastName":"Simpsons","email":"homer_JS@gmail.com","password":"$2a$10$mzRS5euKbFlCEfg0MtqdtOAJfywunYN./gQI7iTkfTSh1Xn.WH4gm","admin":true,"image":"default-image.png"},{"id":8,"firstName":"Franco","lastName":"Fernandez","email":"francodel4to@ymail.com","password":"$2a$10$6y2NvICaybmJNjHcpw9Bk.MS5mYrikMVKsh3t9uAMGYVCIjXGpsKi","admin":false,"image":"default.png","tel":"","address":"","pc":"","province":"","city":""},{"id":9,"firstName":"Franco","lastName":"Fernandez","email":"cuentadeprueba@gmail.com","password":"$2a$10$CnC18ACynEHIMnyD1zTtL.QPS4Ni5myqCFunOtHF48cKRGkk/yao2","admin":false,"image":"default.png","tel":"","address":"","pc":""},{"id":10,"firstName":"Franco","email":"francodel4to@gmail.com","password":"$2a$10$3axmx/qQsKHYfq7IeHpTIOjCAJC1p61.7SoyDrh7yf8M6ngiIr/tC","admin":false,"image":"1630638862182_img_.png","lastName":"Fernandez","tel":"11121654654","address":"121315","pc":"1425","province":"","city":""}]
